SPLAT-0.32.dist-info/DESCRIPTION.rst
SPLAT-0.32.dist-info/METADATA
SPLAT-0.32.dist-info/RECORD
SPLAT-0.32.dist-info/WHEEL
SPLAT-0.32.dist-info/metadata.json
SPLAT-0.32.dist-info/top_level.txt
SPLAT-0.32.dist-info/zip-safe
splat/__init__.py
splat/citations.py
splat/core.py
splat/database.py
splat/empirical.py
splat/euclid.py
splat/evolve.py
splat/initialize.py
splat/model.py
splat/photometry.py
splat/plot.py
splat/splat_backup.py
splat/triangle.py
splat/utilities.py
splat/web.py
splat/db/biblibrary.bib
splat/db/code_summary.txt
splat/db/combined_data.txt
splat/db/photometry_data.txt
splat/db/publications.txt
splat/db/source_data.txt
splat/db/spectral_data.txt
splat/db/testing.xlsx
test/__init__.py
test/test_citations.py
test/test_core.py
test/test_database.py
test/test_empirical.py
test/test_evolve.py
test/test_model.py
test/test_photometry.py
test/test_plot.py
test/test_utilities.py
