Metadata-Version: 2.0
Name: SPLAT
Version: 0.32
Summary: SpeX Prism Library Analysis Toolkit
Home-page: http://www.browndwarfs.org/splat/
Author: Adam Burgasser
Author-email: aburgasser@ucsd.edu
License: MIT
Keywords: splat,spectroscopy,spectral analysis,astronomy,astrophysics,ultracool dwarfs,low mass stars,brown dwarfs,spex,prism,classification
Platform: UNKNOWN
Classifier: Development Status :: 3 - Alpha
Classifier: Intended Audience :: Science/Research
Classifier: License :: OSI Approved :: MIT License
Classifier: Operating System :: OS Independent
Classifier: Programming Language :: Python :: 2
Classifier: Programming Language :: Python :: 2.6
Classifier: Programming Language :: Python :: 2.7
Classifier: Programming Language :: Python :: 3
Classifier: Programming Language :: Python :: 3.3
Classifier: Programming Language :: Python :: 3.4
Classifier: Programming Language :: Python :: 3.5
Classifier: Topic :: Scientific/Engineering :: Astronomy
Classifier: Topic :: Scientific/Engineering :: Physics
Requires-Dist: astropy
Requires-Dist: astroquery
Requires-Dist: bokeh
Requires-Dist: flask
Requires-Dist: matplotlib
Requires-Dist: numpy
Requires-Dist: pandas
Requires-Dist: requests
Requires-Dist: scipy
